genie_flow_invoker/invoker/ollama.py
genie_flow_invoker_ollama-0.8.4.dist-info/licenses/NOTICES
genie_flow_invoker_ollama-0.8.4.dist-info/METADATA
genie_flow_invoker_ollama-0.8.4.dist-info/WHEEL
genie_flow_invoker_ollama-0.8.4.dist-info/top_level.txt
genie_flow_invoker_ollama-0.8.4.dist-info/RECORD
