Metadata-Version: 2.4
Name: genie_flow_invoker_ollama
Version: 0.8.4
Summary: Genie Flow Invoker Ollama
Maintainer-email: Willem van Asperen <willem.van.asperen@paconsulting.com>
License-Expression: Apache-2.0
Classifier: Development Status :: 5 - Production/Stable
Classifier: Intended Audience :: Developers
Classifier: Programming Language :: Python :: 3
Classifier: Programming Language :: Python :: 3.11
Classifier: Programming Language :: Python :: 3.12
Classifier: Operating System :: OS Independent
Classifier: Framework :: Pydantic
Classifier: Topic :: Software Development :: Libraries :: Application Frameworks
Classifier: Topic :: Scientific/Engineering :: Artificial Intelligence
Classifier: Typing :: Typed
Requires-Python: >=3.11.0
License-File: NOTICES
Requires-Dist: loguru~=0.7
Requires-Dist: genie-flow-invoker
Requires-Dist: ollama~=0.6.0
Requires-Dist: PyYAML~=6.0.3
Requires-Dist: backoff~=2.2.1
Dynamic: license-file
